[
  {
    "ФИО":"Иванов Алексей Дмитриевич",
    "1-й проект":"Интеллектуальный помощник для студентов",
    "2-й проект":"Разработка рекомендательной системы для онлайн-курсов",
    "3-й проект":"Прогнозирование успеваемости студентов"
  },
  {
    "ФИО":"Смирнова Елена Викторовна",
    "1-й проект":"Разработка чат-бота для психологической поддержки",
    "2-й проект":"ИИ для анализа эмоционального состояния на видеозаписях",
    "3-й проект":"Прогнозирование успеваемости студентов"
  },
  {
    "ФИО":"Кузнецов Илья Сергеевич",
    "1-й проект":"Оценка устойчивости финансовых моделей",
    "2-й проект":"Прогнозирование спроса на продукты питания",
    "3-й проект":"Анализ социальных сетей в политических исследованиях"
  },
  {
    "ФИО":"Михайлова Дарья Андреевна",
    "1-й проект":"Автоматизация анализа юридических документов",
    "2-й проект":"Криптографическая платформа для хранения данных",
    "3-й проект":"Система анализа научных публикаций"
  },
  {
    "ФИО":"Петров Никита Алексеевич",
    "1-й проект":"ИИ для оценки UX-дизайна мобильных приложений",
    "2-й проект":"Разработка адаптивной системы тестирования",
    "3-й проект":"Мультимодальные интерфейсы для управления ИИ"
  },
  {
    "ФИО":"Александрова Мария Павловна",
    "1-й проект":"Анализ и классификация фейковых новостей",
    "2-й проект":"Генерация художественного текста с помощью ИИ",
    "3-й проект":"Инструмент анализа медиаповестки в реальном времени"
  },
  {
    "ФИО":"Тихонов Артём Михайлович",
    "1-й проект":"Криптографическая платформа для хранения данных",
    "2-й проект":"Обработка медицинских изображений с помощью CNN",
    "3-й проект":"Система анализа научных публикаций"
  },
  {
    "ФИО":"Соколова Наталья Игоревна",
    "1-й проект":"Разработка интерактивной карты культурного наследия",
    "2-й проект":"Создание генеративного чат-агента для музеев",
    "3-й проект":"Цифровая визуализация исторических данных"
  },
  {
    "ФИО":"Григорьев Даниил Романович",
    "1-й проект":"Оптимизация логистических маршрутов с использованием ML",
    "2-й проект":"Прогнозирование спроса на продукты питания",
    "3-й проект":"Оценка устойчивости финансовых моделей"
  },
  {
    "ФИО":"Васильева Ирина Юрьевна",
    "1-й проект":"Анализ социальных сетей в политических исследованиях",
    "2-й проект":"Система визуализации данных для парламентариев",
    "3-й проект":"Инструмент анализа медиаповестки в реальном времени"
  },
  {
    "ФИО":"Октябрина Оскаровна Колесникова",
    "1-й проект":"Криптографическая платформа для хранения данных",
    "2-й проект":"Система анализа научных публикаций",
    "3-й проект":"Обработка медицинских изображений с помощью CNN"
  },
  {
    "ФИО":"Алина Яковлевна Гурьева",
    "1-й проект":"Прогнозирование успеваемости студентов",
    "2-й проект":"Анализ социальных сетей в политических исследованиях",
    "3-й проект":"Разработка адаптивной системы тестирования"
  },
  {
    "ФИО":"Регина Васильевна Большакова",
    "1-й проект":"Генерация художественного текста с помощью ИИ",
    "2-й проект":"ИИ для анализа эмоционального состояния на видеозаписях",
    "3-й проект":"Анализ и классификация фейковых новостей"
  },
  {
    "ФИО":"Викентий Архипович Архипов",
    "1-й проект":"Оптимизация логистических маршрутов с использованием ML",
    "2-й проект":"Прогнозирование спроса на продукты питания",
    "3-й проект":"Оценка устойчивости финансовых моделей"
  },
  {
    "ФИО":"Волкова Иванна Владиславовна",
    "1-й проект":"Цифровая трансформация образовательных программ",
    "2-й проект":"Интеллектуальный помощник для студентов",
    "3-й проект":"ИИ для автоматического создания презентаций"
  },
  {
    "ФИО":"Герасимов Никита Харлампович",
    "1-й проект":"Прогнозирование спроса на продукты питания",
    "2-й проект":"Оптимизация логистических маршрутов с использованием ML",
    "3-й проект":"Оценка устойчивости финансовых моделей"
  },
  {
    "ФИО":"Анжела Филипповна Лукина",
    "1-й проект":"ИИ для оценки UX-дизайна мобильных приложений",
    "2-й проект":"Мультимодальные интерфейсы для управления ИИ",
    "3-й проект":"Разработка адаптивной системы тестирования"
  },
  {
    "ФИО":"Никонов Леонтий Федосеевич",
    "1-й проект":"Криптографическая платформа для хранения данных",
    "2-й проект":"Обработка медицинских изображений с помощью CNN",
    "3-й проект":"Система анализа научных публикаций"
  },
  {
    "ФИО":"Лаврентьев Владислав Давыдович",
    "1-й проект":"Прогнозирование спроса на продукты питания",
    "2-й проект":"Генерация художественного текста с помощью ИИ",
    "3-й проект":"ИИ для анализа эмоционального состояния на видеозаписях"
  },
  {
    "ФИО":"Моисей Жоресович Князев",
    "1-й проект":"Создание генеративного чат-агента для музеев",
    "2-й проект":"Генерация художественного текста с помощью ИИ",
    "3-й проект":"ИИ для автоматического создания презентаций"
  }
]